MANIFEST.in
distribute_setup.py
setup.py
bin/pygameui-kitchensink.py
pygameui/__init__.py
pygameui/alert.py
pygameui/button.py
pygameui/callback.py
pygameui/checkbox.py
pygameui/colors.py
pygameui/dialog.py
pygameui/flipbook.py
pygameui/focus.py
pygameui/grid.py
pygameui/imagebutton.py
pygameui/imageview.py
pygameui/kvc.py
pygameui/label.py
pygameui/listview.py
pygameui/notification.py
pygameui/progress.py
pygameui/render.py
pygameui/resource.py
pygameui/scene.py
pygameui/scroll.py
pygameui/select.py
pygameui/slider.py
pygameui/spinner.py
pygameui/textfield.py
pygameui/theme.py
pygameui/view.py
pygameui/window.py
pygameui.egg-info/PKG-INFO
pygameui.egg-info/SOURCES.txt
pygameui.egg-info/dependency_links.txt
pygameui.egg-info/requires.txt
pygameui.egg-info/top_level.txt
pygameui/resources/fonts/.DS_Store
pygameui/resources/fonts/bold.ttf
pygameui/resources/fonts/font info.txt
pygameui/resources/fonts/regular.ttf
pygameui/resources/images/info.png
pygameui/resources/images/logo.png
pygameui/resources/images/shadow.png
pygameui/resources/images/spinner.png
pygameui/resources/images/star.png