Metadata-Version: 1.0
Name: pygameui
Version: 0.2.0
Summary: GUI framework for Pygame
Home-page: https://github.com/fictorial/pygameui
Author: Brian Hammond
Author-email: brian@fictorial.com
License: MIT
Keywords: UI GUI Pygame button scrollbar progress slider user interface
Platform: UNKNOWN
Classifier: Development Status :: 4 - Beta
Classifier: Intended Audience :: Developers
Classifier: License :: OSI Approved :: MIT License
Classifier: Operating System :: Microsoft :: Windows
Classifier: Operating System :: MacOS :: MacOS X
Classifier: Operating System :: POSIX :: Linux
Classifier: Programming Language :: Python :: 2 :: Only
Classifier: Topic :: Desktop Environment
Classifier: Topic :: Games/Entertainment
Classifier: Topic :: Multimedia
Classifier: Topic :: Software Development
Classifier: Topic :: Software Development :: Libraries :: pygame
Classifier: Topic :: Software Development :: Widget Sets
